setup.py
quandlpy/__init__.py
quandlpy/quandlpy.py
quandlpy.egg-info/PKG-INFO
quandlpy.egg-info/SOURCES.txt
quandlpy.egg-info/dependency_links.txt
quandlpy.egg-info/requires.txt
quandlpy.egg-info/top_level.txt