Metadata-Version: 1.0
Name: quandlpy
Version: 0.1.3
Summary: simple Quandl python wrapper
Home-page: https://github.com/ack8006/quandl-py
Author: Alex Takata
Author-email: takata.alex@gmail.com
License: MIT
Keywords: Quandl Python Wrapper
Platform: UNKNOWN
